Workbook

Sheet Istruzioni
A1: KMoney — Modello economico
A2: Allegato al documento di strategia del 14/08/2026. Tutte le celle BLU sono modificabili: il resto si ricalcola.
A5: LEGENDA COLORI
A6: Testo blu | B6: Parametro modificabile da te. È l'unica cosa che devi toccare.
A7: Testo nero | B7: Formula calcolata. Non modificare: si aggiorna da sola.
A8: Testo verde | B8: Riferimento a un altro foglio del modello.
A9: Sfondo giallo | B9: Ipotesi chiave: il risultato è molto sensibile a questo numero.
A10: Sfondo rosa | B10: Voce di costo o di rischio.
A12: FOGLI
A13: Parametri | B13: Tutti i parametri del modello in un unico posto. Parti da qui.
A14: Sconto 25% | B14: La matematica del bonus: perché il 25% sulla ricarica è al massimo un 20% di sconto.
A15: Margine ricarica | B15: Margine KMoney per singola ricarica, al variare della maturità dell'agente.
A16: Compenso agente | B16: Quanto guadagna realmente un agente, per scenario di portafoglio clienti.
A17: Proiezione 12 mesi | B17: Conto economico mese per mese: ricavi, costi del piano, margine netto.
A18: Esposizione Ky | B18: Passività del circuito e riserva di cassa raccomandata.
A19: Break-even BasiQ | B19: Quante ricariche servono perché un evento BasiQ si ripaghi.
A20: Stress test | B20: Cosa succede se per 6 mesi non entra nessun nuovo agente.
A22: FONTE DEI NUMERI
A23: Verificati nel codice | B23: Percentuali dirette e indirette, gating, bonus di struttura, margine KNM, soglie qualifiche: letti da MlmCommissionEngine.php, MlmBonusService.php, MlmPointsService.php, MlmRankEngine.php e dalle migration mlm_rank_requirements / ky_cards (repository kmoney-app, 14/08/2026).
A24: Ipotesi dichiarate | B24: Ricarica media, tassi di conversione, crescita clienti, costi fissi, quota di Ky rispesi: sono MIE IPOTESI, segnate in giallo. Sostituiscile con i tuoi dati reali appena li hai.
A25: Non disponibili | B25: Il catalogo KY Card reale in produzione e le transaction_fees attive non erano leggibili dal repository: i valori usati qui sono ipotesi da confermare.

Sheet Parametri
A1: Parametri del modello
A2: Modifica solo le celle blu. Le celle gialle sono le ipotesi a cui il risultato è più sensibile.
A4: Parametro | B4: Valore | C4: Unità | D4: Fonte / nota
A5: PRODOTTO
A6: Bonus sulla ricarica (b) | B6: 0.25 | C6: % | D6: Configurabile per singola KY Card (ky_cards.bonus_value). NON è hardcoded nel codice: il 25% è una scelta di catalogo.
A7: Margine KNM su ricarica (m) — 'Prov K' | B7: 0.3 | C7: % | D7: SystemSetting::mlmKnmMarginPercent(), default 30. Verificato in MlmCommissionEngine.php.
A8: Taglio ricarica di riferimento | B8: 120 | C8: EUR | D8: Soglia sotto la quale, oggi, una ricarica non genera punti MLM (backfill ky_cards).
A9: Ricarica media per cliente attivo | B9: 150 | C9: EUR | D9: IPOTESI. Sostituire con il dato reale appena disponibile.
A10: % clienti attivi che ricaricano nel mese | B10: 0.6 | C10: % | D10: IPOTESI.
A11: Fee media di transazione incassata | B11: 0 | C11: EUR | D11: transaction_fees è configurabile ma i valori di produzione non sono noti. Impostato a 0 in via prudenziale.
A13: PIANO COMPENSI (verificato nel codice)
A14: % diretta — agente nuovo (12 punti) | B14: 0.1 | C14: % | D14: MlmCommissionEngine::DIRECT_TABLE
A15: % diretta — agente medio (48 punti) | B15: 0.2 | C15: % | D15: idem
A16: % diretta — agente maturo (200 punti) | B16: 0.4 | C16: % | D16: idem
A17: % indirette L1-L5 sommate | B17: 0.155 | C17: % | D17: 4% + 2% + 1% + 0,5% + 8% = 15,5%. INDIRECT_PERCENTAGES.
A18: % indiretta oltre il L5 (per livello) | B18: 0.005 | C18: % | D18: Solo Top/SuperVisor/Manager.
A19: Costo massimo per evento BasiQ | B19: 200 | C19: EUR | D19: Tetto strutturale: la somma dei payout di una catena è pari all'importo del grado più alto (Manager 200 €). MlmBonusService.
A20: Extra Bonus — Senior | B20: 300 | C20: EUR | D20: MlmAwardService, una tantum alla prima promozione.
A21: Extra Bonus — Top | B21: 3000 | C21: EUR | D21: idem
A22: Extra Bonus — SuperVisor | B22: 5000 | C22: EUR | D22: idem
A23: Extra Bonus — Manager | B23: 20000 | C23: EUR | D23: idem
A24: Bonus Diretti KNM | B24: 0 | C24: EUR | D24: DISATTIVATI il 14/08/2026 (mlm_direct_bonuses_enabled default false).
A26: GATE BASIQ (da decidere — D3)
A27: Punti da ricarica richiesti per BasiQ | B27: 6 | C27: n. | D27: OGGI: 0 (nessun gate). Proposta P0-2. Con card da 120 € = 2 punti, 6 punti = 3 ricariche.
A28: Punti generati da una card da 120 € | B28: 2 | C28: n. | D28: ky_cards.mlm_points, backfill iniziale.
A30: COSTI OPERATIVI
A31: Costo piattaforma / mese | B31: 200 | C31: EUR | D31: IPOTESI: hosting, servizi, gateway.
A32: Costo marketing / mese | B32: 150 | C32: EUR | D32: IPOTESI: materiali, eventi, stampe.
A33: Costo per agente in rete / mese | B33: 50 | C33: EUR | D33: IPOTESI: supporto, materiali, formazione.
A35: CIRCOLARITÀ E RISERVA
A36: % di Ky spesi presso esercenti | B36: 0.75 | C36: % | D36: IPOTESI. È il parametro più importante di tutto il modello: misura se il circuito respira.
A37: % del margine accantonata a riserva Ky | B37: 0.2 | C37: % | D37: RACCOMANDAZIONE.
A38: % del margine accantonata a riserva payout | B38: 0.3 | C38: % | D38: RACCOMANDAZIONE.

Sheet Sconto 25%
A1: La matematica del bonus del 25%
A2: Il bonus del 25% sulla ricarica NON è uno sconto del 25% sullo scontrino.
A4: FORMULA
A5: Sconto implicito sui Ky | B5: =1-1/(1+Parametri!$B$6) -> 0.2 | C5: formula: 1 − 1/(1+b)
A6: Sconto effettivo sullo scontrino | C6: formula: quota accettata in Ky × sconto implicito
A9: Quota accettata in Ky dall'esercente | B9: Su 100 € di spesa: pagati in Ky | C9: Su 100 € di spesa: pagati in EUR | D9: Costo reale dei Ky usati (EUR) | E9: Esborso totale del cliente | F9: Risparmio | G9: Sconto effettivo
A10: 1 | B10: =100*A10 -> 100 | C10: =100-B10 -> 0 | D10: =B10/(1+Parametri!$B$6) -> 80 | E10: =C10+D10 -> 80 | F10: =100-E10 -> 20 | G10: =F10/100 -> 0.2
A11: 0.75 | B11: =100*A11 -> 75 | C11: =100-B11 -> 25 | D11: =B11/(1+Parametri!$B$6) -> 60 | E11: =C11+D11 -> 85 | F11: =100-E11 -> 15 | G11: =F11/100 -> 0.15
A12: 0.5 | B12: =100*A12 -> 50 | C12: =100-B12 -> 50 | D12: =B12/(1+Parametri!$B$6) -> 40 | E12: =C12+D12 -> 90 | F12: =100-E12 -> 10 | G12: =F12/100 -> 0.1
A13: 0.25 | B13: =100*A13 -> 25 | C13: =100-B13 -> 75 | D13: =B13/(1+Parametri!$B$6) -> 20 | E13: =C13+D13 -> 95 | F13: =100-E13 -> 5 | G13: =F13/100 -> 0.05
A14: 0 | B14: =100*A14 -> 0 | C14: =100-B14 -> 100 | D14: =B14/(1+Parametri!$B$6) -> 0 | E14: =C14+D14 -> 100 | F14: =100-E14 -> 0 | G14: =F14/100 -> 0
A17: COME SI DICE, COME NON SI DICE
A18: NO | B18: "25% di sconto su tutto" — falso: non esiste alcuno scenario in cui il cliente risparmi il 25%.
A19: NO | B19: "Risparmi un quarto" — stessa cosa detta diversamente.
A20: SI | B20: "Ricarichi 100 €, ne hai 125 da spendere. Sullo scontrino risparmi dal 5% al 20% a seconda di quanto quel negozio accetta in KMoney."
A21: SI | B21: "Su ogni negozio trovi scritta la percentuale, prima di entrare."

Sheet Margine ricarica
A1: Margine KMoney per singola ricarica
A2: Quanto resta a KMoney dopo aver pagato le commissioni dell'intera catena.
A4: Scenario | B4: Ricarica | C4: Prov K (base commissioni) | D4: % diretta | E4: % indiretta | F4: Commissioni totali | G4: Margine residuo | H4: % su ricarica
A5: Agente nuovo (12 pt), nessuna downline | B5: =Parametri!$B$8 -> 120 | C5: =B5*Parametri!$B$7 -> 36 | D5: =Parametri!$B$14 -> 0.1 | E5: =0 -> 0 | F5: =C5*(D5+E5) -> 3.6 | G5: =C5-F5 -> 32.4 | H5: =G5/B5 -> 0.27
A6: Agente medio (48 pt), 1 livello indiretto attivo | B6: =Parametri!$B$8 -> 120 | C6: =B6*Parametri!$B$7 -> 36 | D6: =Parametri!$B$15 -> 0.2 | E6: =0.04 -> 0.04 | F6: =C6*(D6+E6) -> 8.64 | G6: =C6-F6 -> 27.36 | H6: =G6/B6 -> 0.228
A7: Agente maturo (200 pt), 5 livelli indiretti pieni | B7: =Parametri!$B$8 -> 120 | C7: =B7*Parametri!$B$7 -> 36 | D7: =Parametri!$B$16 -> 0.4 | E7: =Parametri!$B$17 -> 0.155 | F7: =C7*(D7+E7) -> 19.98 | G7: =C7-F7 -> 16.02 | H7: =G7/B7 -> 0.1335
A8: Come sopra + 10 livelli estesi (Top+) | B8: =Parametri!$B$8 -> 120 | C8: =B8*Parametri!$B$7 -> 36 | D8: =Parametri!$B$16 -> 0.4 | E8: =Parametri!$B$17+10*Parametri!$B$18 -> 0.205 | F8: =C8*(D8+E8) -> 21.78 | G8: =C8-F8 -> 14.22 | H8: =G8/B8 -> 0.1185
A11: TETTO DI SICUREZZA RACCOMANDATO (P0-3a)
A12: Cap sulle commissioni per riga di Prov K | B12: 0.8
A13: Livelli estesi (Top+) necessari per superare il 100% di Prov K | B13: =ROUNDUP((1-Parametri!$B$16-Parametri!$B$17)/Parametri!$B$18,0) -> 89 | C13: Oggi implausibile, ma non impossibile per costruzione: il motore non ha alcun tetto.

Sheet Compenso agente
A1: Compenso reale dell'agente
A2: Solo commissioni dirette. La base commissionabile è la RICARICA, pagata una sola volta per ricarica.
A4: Scenario di portafoglio | B4: N. clienti che ricaricano | C4: Ricarica media | D4: Volume mensile | E4: Prov K | F4: % diretta | G4: Commissione diretta / mese | H4: Nota
A5: Avvio | B5: 5 | C5: =Parametri!$B$8 -> 120 | D5: =B5*C5 -> 600 | E5: =D5*Parametri!$B$7 -> 180 | F5: =Parametri!$B$14 -> 0.1 | G5: =E5*F5 -> 18 | H5: Primo mese operativo.
A6: Consolidamento | B6: 20 | C6: =Parametri!$B$8 -> 120 | D6: =B6*C6 -> 2400 | E6: =D6*Parametri!$B$7 -> 720 | F6: =Parametri!$B$15 -> 0.2 | G6: =E6*F6 -> 144 | H6: Corrisponde grosso modo al 3°-4° mese dello scenario realistico.
A7: Maturità | B7: 50 | C7: =Parametri!$B$8 -> 120 | D7: =B7*C7 -> 6000 | E7: =D7*Parametri!$B$7 -> 1800 | F7: =0.25 -> 0.25 | G7: =E7*F7 -> 450 | H7: Richiede ~96 punti attivi: sostenibile solo con ricariche ricorrenti.
A8: Maturità alta | B8: 100 | C8: =Parametri!$B$8 -> 120 | D8: =B8*C8 -> 12000 | E8: =D8*Parametri!$B$7 -> 3600 | F8: =Parametri!$B$16 -> 0.4 | G8: =E8*F8 -> 1440 | H8: Richiede 200 punti attivi. Pochi agenti ci arrivano.
A11: AVVERTENZA DA RIPETERE A OGNI CANDIDATO AGENTE
A12: Questi importi presuppongono che OGNI cliente ricarichi OGNI mese. La base commissionabile è la singola ricarica, pagata una sola volta (MlmPointsService::createCommissionBaseEntry, decisione del 22/07/2026). Un cliente che ricarica una volta e poi smette genera commissione una volta sola. Non esiste rendita.

Sheet Proiezione 12 mesi
A1: Proiezione a 12 mesi — scenario realistico
A2: Clienti attivi ed esercenti sono IPOTESI (celle blu). Tutto il resto si calcola.
A4: Mese | B4: Clienti attivi | C4: Esercenti | D4: Agenti in rete | E4: Volume ricariche | F4: Prov K | G4: Commissioni | H4: Bonus struttura | I4: Extra Bonus | J4: Costi fissi | K4: Margine netto
A5: 1 | B5: 5 | C5: 4 | D5: 1 | E5: =B5*Parametri!$B$10*Parametri!$B$9 -> 450 | F5: =E5*Parametri!$B$7 -> 135 | G5: =F5*MIN(Parametri!$B$16,Parametri!$B$14+(B5/1000)) -> 14.175 | H5: =0*Parametri!$B$19 -> 0 | I5: 0 | J5: =Parametri!$B$31+Parametri!$B$32+D5*Parametri!$B$33 -> 400 | K5: =F5-G5-H5-I5-J5 -> -279.175
A6: 2 | B6: 15 | C6: 7 | D6: 1 | E6: =B6*Parametri!$B$10*Parametri!$B$9 -> 1350 | F6: =E6*Parametri!$B$7 -> 405 | G6: =F6*MIN(Parametri!$B$16,Parametri!$B$14+(B6/1000)) -> 46.575 | H6: =0*Parametri!$B$19 -> 0 | I6: 0 | J6: =Parametri!$B$31+Parametri!$B$32+D6*Parametri!$B$33 -> 400 | K6: =F6-G6-H6-I6-J6 -> -41.575
A7: 3 | B7: 30 | C7: 12 | D7: 1 | E7: =B7*Parametri!$B$10*Parametri!$B$9 -> 2700 | F7: =E7*Parametri!$B$7 -> 810 | G7: =F7*MIN(Parametri!$B$16,Parametri!$B$14+(B7/1000)) -> 105.3 | H7: =0*Parametri!$B$19 -> 0 | I7: 0 | J7: =Parametri!$B$31+Parametri!$B$32+D7*Parametri!$B$33 -> 400 | K7: =F7-G7-H7-I7-J7 -> 304.7
A8: 4 | B8: 45 | C8: 15 | D8: 1 | E8: =B8*Parametri!$B$10*Parametri!$B$9 -> 4050 | F8: =E8*Parametri!$B$7 -> 1215 | G8: =F8*MIN(Parametri!$B$16,Parametri!$B$14+(B8/1000)) -> 176.175 | H8: =1*Parametri!$B$19 -> 200 | I8: 0 | J8: =Parametri!$B$31+Parametri!$B$32+D8*Parametri!$B$33 -> 400 | K8: =F8-G8-H8-I8-J8 -> 438.825
A9: 5 | B9: 62 | C9: 18 | D9: 2 | E9: =B9*Parametri!$B$10*Parametri!$B$9 -> 5580 | F9: =E9*Parametri!$B$7 -> 1674 | G9: =F9*MIN(Parametri!$B$16,Parametri!$B$14+(B9/1000)) -> 271.188 | H9: =0*Parametri!$B$19 -> 0 | I9: 0 | J9: =Parametri!$B$31+Parametri!$B$32+D9*Parametri!$B$33 -> 450 | K9: =F9-G9-H9-I9-J9 -> 952.812
A10: 6 | B10: 80 | C10: 21 | D10: 2 | E10: =B10*Parametri!$B$10*Parametri!$B$9 -> 7200 | F10: =E10*Parametri!$B$7 -> 2160 | G10: =F10*MIN(Parametri!$B$16,Parametri!$B$14+(B10/1000)) -> 388.8 | H10: =1*Parametri!$B$19 -> 200 | I10: 0 | J10: =Parametri!$B$31+Parametri!$B$32+D10*Parametri!$B$33 -> 450 | K10: =F10-G10-H10-I10-J10 -> 1121.2
A11: 7 | B11: 100 | C11: 24 | D11: 2 | E11: =B11*Parametri!$B$10*Parametri!$B$9 -> 9000 | F11: =E11*Parametri!$B$7 -> 2700 | G11: =F11*MIN(Parametri!$B$16,Parametri!$B$14+(B11/1000)) -> 540 | H11: =1*Parametri!$B$19 -> 200 | I11: 300 | J11: =Parametri!$B$31+Parametri!$B$32+D11*Parametri!$B$33 -> 450 | K11: =F11-G11-H11-I11-J11 -> 1210
A12: 8 | B12: 122 | C12: 27 | D12: 2 | E12: =B12*Parametri!$B$10*Parametri!$B$9 -> 10980 | F12: =E12*Parametri!$B$7 -> 3294 | G12: =F12*MIN(Parametri!$B$16,Parametri!$B$14+(B12/1000)) -> 731.268 | H12: =0*Parametri!$B$19 -> 0 | I12: 0 | J12: =Parametri!$B$31+Parametri!$B$32+D12*Parametri!$B$33 -> 450 | K12: =F12-G12-H12-I12-J12 -> 2112.732
A13: 9 | B13: 148 | C13: 31 | D13: 3 | E13: =B13*Parametri!$B$10*Parametri!$B$9 -> 13320 | F13: =E13*Parametri!$B$7 -> 3996 | G13: =F13*MIN(Parametri!$B$16,Parametri!$B$14+(B13/1000)) -> 991.008 | H13: =1*Parametri!$B$19 -> 200 | I13: 0 | J13: =Parametri!$B$31+Parametri!$B$32+D13*Parametri!$B$33 -> 500 | K13: =F13-G13-H13-I13-J13 -> 2304.992
A14: 10 | B14: 176 | C14: 35 | D14: 3 | E14: =B14*Parametri!$B$10*Parametri!$B$9 -> 15840 | F14: =E14*Parametri!$B$7 -> 4752 | G14: =F14*MIN(Parametri!$B$16,Parametri!$B$14+(B14/1000)) -> 1311.552 | H14: =1*Parametri!$B$19 -> 200 | I14: 0 | J14: =Parametri!$B$31+Parametri!$B$32+D14*Parametri!$B$33 -> 500 | K14: =F14-G14-H14-I14-J14 -> 2740.448
A15: 11 | B15: 206 | C15: 38 | D15: 3 | E15: =B15*Parametri!$B$10*Parametri!$B$9 -> 18540 | F15: =E15*Parametri!$B$7 -> 5562 | G15: =F15*MIN(Parametri!$B$16,Parametri!$B$14+(B15/1000)) -> 1701.972 | H15: =1*Parametri!$B$19 -> 200 | I15: 300 | J15: =Parametri!$B$31+Parametri!$B$32+D15*Parametri!$B$33 -> 500 | K15: =F15-G15-H15-I15-J15 -> 2860.028
A16: 12 | B16: 240 | C16: 42 | D16: 3 | E16: =B16*Parametri!$B$10*Parametri!$B$9 -> 21600 | F16: =E16*Parametri!$B$7 -> 6480 | G16: =F16*MIN(Parametri!$B$16,Parametri!$B$14+(B16/1000)) -> 2203.2 | H16: =1*Parametri!$B$19 -> 200 | I16: 3000 | J16: =Parametri!$B$31+Parametri!$B$32+D16*Parametri!$B$33 -> 500 | K16: =F16-G16-H16-I16-J16 -> 576.8
A17: TOT | E17: =SUM(E5:E16) -> 110610 | F17: =SUM(F5:F16) -> 33183 | G17: =SUM(G5:G16) -> 8481.213 | H17: =SUM(H5:H16) -> 1400 | I17: =SUM(I5:I16) -> 3600 | J17: =SUM(J5:J16) -> 5400 | K17: =SUM(K5:K16) -> 14301.787
A19: Mese di break-even | C19: =IFERROR(MATCH(TRUE(),INDEX(K5:K16>0,0),0),"mai") -> 3
A20: Margine cumulato a 12 mesi | C20: =K17 -> 14301.787
A21: Rapporto commissioni : bonus | C21: =G17/MAX(1,H17+I17) -> 1.6962426 | E21: Target raccomandato: ≥ 3,00x. Sotto 1,5x l'incentivo primario si avvicina al reclutamento (art. 5 L.173/2005).

Sheet Esposizione Ky
A1: Esposizione in Ky e riserva di cassa
A2: I Ky oggi non hanno scadenza e non sono segregati: la passività è permanente e cumulativa.
A5: Volume ricariche a 12 mesi (EUR incassati) | B5: ='Proiezione 12 mesi'!E17 -> 110610 | C5: Somma della proiezione.
A6: Ky emessi a fronte delle ricariche | B6: =B5*(1+Parametri!$B$6) -> 138262.5 | C6: Base + bonus.
A7: di cui Ky promozionali (il bonus) | B7: =B5*Parametri!$B$6 -> 27652.5 | C7: OGGI NON SEPARABILI NEL DATABASE: serve l'intervento P0-1.
A8: Copertura in euro di ogni Ky emesso | B8: =B5/B6 -> 0.8 | C8: Pari a 1/(1+b). Ogni Ky in circolo è coperto per questa quota da euro realmente incassati.
A9: Ky spesi presso esercenti | B9: =B6*Parametri!$B$36 -> 103696.88 | C9: Dipende dalla circolarità del circuito: è il parametro più critico.
A10: Ky fermi nei wallet dei clienti (passività) | B10: =B6-B9 -> 34565.625 | C10: Cresce ogni mese se la spesa non tiene il passo dell'emissione.
A12: RISERVA RACCOMANDATA
A13: Prov K generato a 12 mesi | B13: ='Proiezione 12 mesi'!F17 -> 33183 | C13: Dalla proiezione.
A14: Riserva a copertura dei Ky in circolo | B14: =B13*Parametri!$B$37 -> 6636.6 | C14: % del margine accantonata.
A15: Riserva per i payout MLM | B15: =B13*Parametri!$B$38 -> 9954.9 | C15: Deve arrivare a coprire il massimo Extra Bonus attivabile nel semestre.
A16: Massimo Extra Bonus teorico (Manager) | B16: =Parametri!$B$23 -> 20000 | C16: Se un agente è vicino a Manager, la riserva payout deve raggiungere questa cifra.
A17: Riserva payout sufficiente? | B17: =IF(B15>=B16,"SI","NO — servono ulteriori "&TEXT(B16-B15,"€#,##0")) -> NO — servono ulteriori €10,045 | C17: Controllo automatico.

Sheet Break-even BasiQ
A1: Quanto deve costare un evento BasiQ
A2: Decisione D3: quanti punti da ricarica richiedere perché l'evento si ripaghi.
A5: Costo massimo di un evento BasiQ | B5: =Parametri!$B$19 -> 200 | C5: Tetto strutturale verificato: la somma dei payout di una catena è pari all'importo del grado più alto presente (Manager, 200 €).
A6: Margine KNM sulle ricariche | B6: =Parametri!$B$7 -> 0.3 | C6: Prov K.
A7: Ricariche necessarie per coprire l'evento | B7: =B5/B6 -> 666.66667 | C7: Volume di ricariche che genera esattamente 200 € di Prov K.
A9: CON IL GATE PROPOSTO (P0-2)
A10: Punti da ricarica richiesti | B10: =Parametri!$B$27 -> 6 | C10: Parametro proposto. OGGI il gate NON esiste: BasiQ scatta con 12 punti di qualunque origine.
A11: Punti per card da 120 € | B11: =Parametri!$B$28 -> 2 | C11: ky_cards.mlm_points.
A12: Ricariche minime richieste (n.) | B12: =B10/B11 -> 3
A13: Volume minimo generato | B13: =B12*Parametri!$B$8 -> 360
A14: Prov K generato | B14: =B13*Parametri!$B$7 -> 108
A15: Copertura del costo dell'evento | B15: =B14/B5 -> 0.54 | C15: Se sotto il 100%, ogni evento BasiQ è finanziato solo in parte dal fatturato che lo ha generato.
A17: Punti da ricarica per copertura al 100% | B17: =ROUNDUP(B7/Parametri!$B$8*Parametri!$B$28,0) -> 12 | C17: Valore da impostare nel parametro se vuoi che il piano si autofinanzi evento per evento.

Sheet Stress test
A1: Stress test: 6 mesi senza nuovi agenti
A2: Mesi 7-12 della proiezione, con zero nuovi ingressi in rete.
A4: Voce | B4: Con nuovi agenti | C4: Senza nuovi agenti | D4: Differenza | E4: Perché
A5: Prov K (ricavo) | B5: =SUM('Proiezione 12 mesi'!F11:F16) -> 26784 | C5: =B5*0.82 -> 21962.88 | D5: =C5-B5 -> -4821.12 | E5: Le ricariche continuano, ma la rete cresce più lentamente (2 agenti invece di 3). La riduzione dell'18% è un'IPOTESI.
A6: Commissioni | B6: =SUM('Proiezione 12 mesi'!G11:G16) -> 7479 | C6: =B6*0.84 -> 6282.36 | D6: =C6-B6 -> -1196.64 | E6: Scendono in proporzione al minor volume.
A7: Bonus di struttura | B7: =SUM('Proiezione 12 mesi'!H11:H16) -> 1000 | C7: 0 | D7: =C7-B7 -> -1000 | E7: AZZERATI: scattano solo su eventi BasiQ, che richiedono nuovi agenti entro 30 giorni dall'attivazione.
A8: Extra Bonus | B8: =SUM('Proiezione 12 mesi'!I11:I16) -> 3600 | C8: 0 | D8: =C8-B8 -> -3600 | E8: Quasi azzerati: le qualifiche richiedono Basic al 1° livello e colonne, che senza nuovi ingressi non si formano.
A9: Costi fissi | B9: =SUM('Proiezione 12 mesi'!J11:J16) -> 2900 | C9: =B9*0.9 -> 2610 | D9: =C9-B9 -> -290 | E9: Meno agenti in rete da supportare.
A11: MARGINE NETTO (6 mesi) | B11: =B5-B6-B7-B8-B9 -> 11805 | C11: =C5-C6-C7-C8-C9 -> 13070.52 | D11: =C11-B11 -> 1265.52 | E11: Se la differenza è positiva, KMoney sta MEGLIO senza nuovi agenti.
A13: Verdetto automatico | B13: =IF(C11>=B11,"Il modello AZIENDALE regge (margine invariato o migliore).","Il modello aziendale NON regge senza nuovi agenti.") -> Il modello AZIENDALE regge (margine invariato o migliore).
A15: MA ATTENZIONE — il punto che conta davvero
A16: Il modello aziendale regge, ma il REDDITO DELL'AGENTE crolla: perde l'intera componente bonus. Questo è esattamente il test dell'art. 5 c.1 L. 173/2005: se il guadagno crolla quando smetti di reclutare, l'incentivo primario è il reclutamento. La risposta non è legale ma di prodotto: introdurre una commissione ricorrente sulle transazioni dei clienti presso gli esercenti (intervento P0-3b), così il reddito cresce con l'USO e non con gli ingressi in rete.
